drb/drivers/swift/__init__.py
drb/drivers/swift/_version.py
drb/drivers/swift/swift.py
drb/topics/swift/__init__.py
drb/topics/swift/cortex.yml
drb_driver_swift-1.3.0.dist-info/LICENCE.txt
drb_driver_swift-1.3.0.dist-info/METADATA
drb_driver_swift-1.3.0.dist-info/WHEEL
drb_driver_swift-1.3.0.dist-info/entry_points.txt
drb_driver_swift-1.3.0.dist-info/top_level.txt
drb_driver_swift-1.3.0.dist-info/RECORD
