Metadata-Version: 2.1
Name: drb-driver-swift
Version: 1.3.0
Summary: DRB OpenStack Swift driver
Home-page: https://gitlab.com/drb-python/impl/swift
Author: GAEL Systems
Author-email: drb-python@gael.fr
License: LGPLv3
Project-URL: Documentation, https://drb-python.gitlab.io/drb-python/impl/swift
Project-URL: Source, https://gitlab.com/drb-python/impl/swift
Classifier: Programming Language :: Python :: 3.8
Classifier: Environment :: Plugins
Classifier: License :: OSI Approved :: GNU Lesser General Public License v3 (LGPLv3)
Classifier: Operating System :: OS Independent
Requires-Python: >=3.8
License-File: LICENCE.txt
Requires-Dist: drb ~=2.2.0
Requires-Dist: drb-driver-http ~=1.3.1
Requires-Dist: python-swiftclient ~=4.1.0
